{
  "project_info": {
    "project_number": "1070387548455",
    "project_id": "project-food-84f07",
    "storage_bucket": "project-food-84f07.appspot.com"
  },
  "client": [
    {
      "client_info": {
        "mobilesdk_app_id": "1:1070387548455:android:ebd343212d52ca57f8d902",
        "android_client_info": {
          "package_name": "com.example.project_food"
        }
      },
      "oauth_client": [],
      "api_key": [
        {
          "current_key": "AIzaSyBeyWyO2voAESWW6fAzALG-wuesYy03g8M"
        }
      ],
      "services": {
        "appinvite_service": {
          "other_platform_oauth_client": []
        }
      }
    }
  ],
  "configuration_version": "1"
}